{
    "version": "0.0.34",
    "architecture": {
        "64bit": {
            "url": "https://github.com/avivsinai/jenkins-cli/releases/download/v0.0.34/jk_0.0.34_windows_x86_64.zip",
            "bin": [
                "jk.exe"
            ],
            "hash": "6b2c9bf99f2180129831468352156fcff1d32a1f48ff09bfe5346ee57c4b169d"
        }
    },
    "homepage": "https://github.com/avivsinai/jenkins-cli",
    "license": "MIT",
    "description": "CLI for Jenkins - GitHub CLI-style workflows for Jenkins controllers"
}
